{
  "country": "France",
  "countryCode": "FRANCE",
  "countryFlag": "🇫🇷",
  "url": "https://eurovision.tv/participant/slimane-2024",
  "artistName": "Slimane",
  "artistImage": "https://eurovision.tv/sites/default/files/styles/teaser/public/media/image/2024-03/422b352c-cda4-49e5-9acc-7edd24957b81.jpg?h=f2593e8e&itok=I0L91fdJ",
  "artistDescription": "From the piano bars of Paris Pigalle, where he started, to his sold-out arena tours, Slimane’s journey is an ode to perseverance, talent and passion.",
  "songName": "Mon amour",
  "songEmbedUrl": "https://youtu.be/tfoOop2HXxQ",
  "score": 0
}